setup.py
distributions_most_common/Binomialdistribution.py
distributions_most_common/Gaussiandistribution.py
distributions_most_common/Generaldistribution.py
distributions_most_common/__init__.py
distributions_most_common.egg-info/PKG-INFO
distributions_most_common.egg-info/SOURCES.txt
distributions_most_common.egg-info/dependency_links.txt
distributions_most_common.egg-info/not-zip-safe
distributions_most_common.egg-info/top_level.txt